Workbook

Sheet 假设
A1: 比亚迪股份 (1211.HK) DCF — 核心假设
A2: 单位：亿元人民币（另注明除外）。蓝色=手工输入；黄色底=关键假设，可直接修改；黑色=公式。
A3: 市场数据
A4: 估值基准日 | B4: =DATE(2026,10,10) -> 46305 | C4: 今日；用于计算 2026 年剩余期间
A5: H股股价 (HK$) | B5: 72.95 | C5: 腾讯财经 01211 行情页 2026-10-08 盘中价 72.95 港元（昨收 74.55）；请用最新收盘价覆盖
A6: 港元兑人民币 (1 HKD = ? CNY) | B6: 0.91 | C6: 假设值；81211 人民币柜台 10/7 收 63.7 元，与 HK$~70 一致
A7: 总股本 (亿股，A+H) | B7: 91.17 | C7: 2025 年 7 月 10 送 8 转 12 后总股本 9,117,197,565 股（2025 年报）
A8: WACC
A9: 无风险利率 | B9: 0.02 | C9: 中国 10 年期国债收益率约 1.8–2.0%（假设）
A10: 股权风险溢价 | B10: 0.065 | C10: 假设，含中国/港股市场溢价
A11: Beta | B11: 1.2 | C11: 假设；港股汽车板块常见 1.1–1.3
A12: 税前债务成本 | B12: 0.03 | C12: 假设，参考人民币贷款利率
A13: 目标负债率 D/(D+E) | B13: 0.1 | C13: 假设；公司有息负债低
A14: 预测期
A15: 有效税率 | B15: 0.18 | C15: 假设：高新技术企业 15% + 海外较高税率混合
A16: 永续增长率 g | B16: 0.025 | C16: 假设
A17: 永续期资本开支 / 折旧 | B17: 1.1 | C17: 假设：永续期维持性资本开支略高于折旧
A18: 增量营运资本 / 增量收入 | B18: 0 | C18: 假设：BYD 营运资本为负（大额应付款）；监管推动缩短账期构成下行风险，故取 0
A19: 资产负债表调整 (2026-06-30)
A20: 货币资金 | B20: 587.4 | C20: 2026 年半年报：货币资金较期初 754.25 亿下降 22.12%
A21: 交易性金融资产等可变现投资 | B21: 800 | C21: 估算：2025 年末“现金储备”约 1,674 亿（含理财），扣除货币资金后约 920 亿；中报数未取得，按 800 亿估
A22: 短期借款 | B22: 600 | C22: 估算：2026Q1 末 662.96 亿；中报数未取得
A23: 长期借款 | B23: 612 | C23: 2026 年半年报：长期借款 612.01 亿
A24: 少数股东权益（估） | B24: 200 | C24: 估算：主要为比亚迪电子少数股东；请以中报为准
A26: 计算得出
A27: 股权成本 Ke | B27: =$B$9+$B$11*$B$10 -> 0.098
A28: 税后债务成本 Kd | B28: =$B$12*(1-$B$15) -> 0.0246
A29: WACC | B29: =(1-$B$13)*$B$27+$B$13*$B$28 -> 0.09066
A30: 2026 年剩余期间（年） | B30: =(DATE(2026,12,31)-$B$4)/365 -> 0.22465753
A31: 净现金（现金+投资−借款） | B31: =$B$20+$B$21-$B$22-$B$23 -> 175.4

Sheet DCF
A1: 比亚迪股份 DCF 预测（亿元人民币）
A2: 历史数据蓝色=报告/媒体披露值；预测期黄色底=可调假设
A4: 年度 | B4: 2024A | C4: 2025A | D4: 2026E | E4: 2027E | F4: 2028E | G4: 2029E | H4: 2030E | I4: 2031E | J4: 2032E | K4: 2033E | L4: 2034E | M4: 2035E
A5: 收入增长率 | C5: =C6/B6-1 -> 0.03461588 | D5: -0.03 | E5: 0.08 | F5: 0.09 | G5: 0.08 | H5: 0.07 | I5: 0.06 | J5: 0.05 | K5: 0.04 | L5: 0.035 | M5: 0.03
A6: 营业收入 | B6: 7771 | C6: 8040 | D6: =C6*(1+D5) -> 7798.8 | E6: =D6*(1+E5) -> 8422.704 | F6: =E6*(1+F5) -> 9180.7474 | G6: =F6*(1+G5) -> 9915.2071 | H6: =G6*(1+H5) -> 10609.272 | I6: =H6*(1+I5) -> 11245.828 | J6: =I6*(1+J5) -> 11808.119 | K6: =J6*(1+K5) -> 12280.444 | ... M6: =L6*(1+M5) -> 13091.567
A7: EBIT 利润率 | C7: 0.05 | D7: 0.045 | E7: 0.05 | F7: 0.055 | G7: 0.058 | H7: 0.06 | I7: 0.06 | J7: 0.06 | K7: 0.06 | L7: 0.06 | M7: 0.06
A8: EBIT | C8: =C6*C7 -> 402 | D8: =D6*D7 -> 350.946 | E8: =E6*E7 -> 421.1352 | F8: =F6*F7 -> 504.9411 | G8: =G6*G7 -> 575.08201 | H8: =H6*H7 -> 636.5563 | I8: =I6*I7 -> 674.74968 | J8: =J6*J7 -> 708.48716 | ... M8: =M6*M7 -> 785.49405
A9: 所得税 | D9: =-D8*假设!$B$15 -> -63.17028 | E9: =-E8*假设!$B$15 -> -75.804336 | F9: =-F8*假设!$B$15 -> -90.889399 | G9: =-G8*假设!$B$15 -> -103.51476 | H9: =-H8*假设!$B$15 -> -114.58013 | I9: =-I8*假设!$B$15 -> -121.45494 | J9: =-J8*假设!$B$15 -> -127.52769 | K9: =-K8*假设!$B$15 -> -132.6288 | ... M9: =-M8*假设!$B$15 -> -141.38893
A10: NOPAT | D10: =D8+D9 -> 287.77572 | E10: =E8+E9 -> 345.33086 | F10: =F8+F9 -> 414.05171 | G10: =G8+G9 -> 471.56725 | H10: =H8+H9 -> 521.97617 | I10: =I8+I9 -> 553.29474 | J10: =J8+J9 -> 580.95947 | K10: =K8+K9 -> 604.19785 | ... M10: =M8+M9 -> 644.10512
A11: 折旧摊销 / 收入 | C11: 0.093 | D11: 0.092 | E11: 0.091 | F11: 0.09 | G11: 0.089 | H11: 0.088 | I11: 0.087 | J11: 0.086 | K11: 0.085 | L11: 0.085 | M11: 0.085
A12: 折旧摊销 | C12: =C6*C11 -> 747.72 | D12: =D6*D11 -> 717.4896 | E12: =E6*E11 -> 766.46606 | F12: =F6*F11 -> 826.26726 | G12: =G6*G11 -> 882.45344 | H12: =H6*H11 -> 933.61591 | I12: =I6*I11 -> 978.38703 | J12: =J6*J11 -> 1015.4983 | ... M12: =M6*M11 -> 1112.7832
A13: 资本开支 / 收入 | C13: 0.195 | D13: 0.14 | E13: 0.12 | F13: 0.11 | G13: 0.105 | H13: 0.1 | I13: 0.097 | J13: 0.095 | K13: 0.094 | L13: 0.094 | M13: =M11*假设!$B$17 -> 0.0935
A14: 资本开支 | C14: =-C6*C13 -> -1567.8 | D14: =-D6*D13 -> -1091.832 | E14: =-E6*E13 -> -1010.7245 | F14: =-F6*F13 -> -1009.8822 | G14: =-G6*G13 -> -1041.0968 | H14: =-H6*H13 -> -1060.9272 | I14: =-I6*I13 -> -1090.8453 | J14: =-J6*J13 -> -1121.7713 | ... M14: =-M6*M13 -> -1224.0616
A15: 增量营运资本 | D15: =-(D6-C6)*假设!$B$18 -> 0 | E15: =-(E6-D6)*假设!$B$18 -> 0 | F15: =-(F6-E6)*假设!$B$18 -> 0 | G15: =-(G6-F6)*假设!$B$18 -> 0 | H15: =-(H6-G6)*假设!$B$18 -> 0 | I15: =-(I6-H6)*假设!$B$18 -> 0 | J15: =-(J6-I6)*假设!$B$18 -> 0 | K15: =-(K6-J6)*假设!$B$18 -> 0 | ... M15: =-(M6-L6)*假设!$B$18 -> 0
A16: 自由现金流 FCFF | D16: =D10+D12+D14+D15 -> -86.56668 | E16: =E10+E12+E14+E15 -> 101.07245 | F16: =F10+F12+F14+F15 -> 230.43676 | G16: =G10+G12+G14+G15 -> 312.92394 | H16: =H10+H12+H14+H15 -> 394.66491 | I16: =I10+I12+I14+I15 -> 440.83646 | J16: =J10+J12+J14+J15 -> 474.6864 | K16: =K10+K12+K14+K15 -> 493.67385 | ... M16: =M10+M12+M14+M15 -> 532.8268
A18: 折现期（年） | D18: =假设!$B$30 -> 0.22465753 | E18: =D18+1 -> 1.2246575 | F18: =E18+1 -> 2.2246575 | G18: =F18+1 -> 3.2246575 | H18: =G18+1 -> 4.2246575 | I18: =H18+1 -> 5.2246575 | J18: =I18+1 -> 6.2246575 | K18: =J18+1 -> 7.2246575 | L18: =K18+1 -> 8.2246575 | M18: =L18+1 -> 9.2246575
A19: 折现因子 | D19: =1/(1+假设!$B$29)^D18 -> 0.98069237 | E19: =1/(1+假设!$B$29)^E18 -> 0.89917332 | F19: =1/(1+假设!$B$29)^F18 -> 0.82443045 | G19: =1/(1+假设!$B$29)^G18 -> 0.75590051 | H19: =1/(1+假设!$B$29)^H18 -> 0.69306705 | I19: =1/(1+假设!$B$29)^I18 -> 0.63545656 | J19: =1/(1+假设!$B$29)^J18 -> 0.58263488 | K19: =1/(1+假设!$B$29)^K18 -> 0.53420395 | ... M19: =1/(1+假设!$B$29)^M18 -> 0.44908477
A20: FCFF 现值 | D20: =D16*D19*假设!$B$30 -> -19.072365 | E20: =E16*E19 -> 90.881648 | F20: =F16*F19 -> 189.97908 | G20: =G16*G19 -> 236.53936 | H20: =H16*H19 -> 273.52924 | I20: =I16*I19 -> 280.13242 | J20: =J16*J19 -> 276.56885 | K20: =K16*K19 -> 263.72252 | L20: =L16*L19 -> 250.26389 | M20: =M16*M19 -> 239.2844
A21: 注：2026E 现金流仅计入基准日后剩余部分（按剩余期间比例）
A22: 参考：归母净利润 | B22: 402.5 | C22: 326.2
A23: 参考：经营现金流 | B23: 1334.5 | C23: 591.4
A26: 估值汇总
A27: 预测期 FCFF 现值合计 | B27: =SUM(D20:M20) -> 2081.829
A28: 终值（Gordon 模型，2035E 末） | B28: =M16*(1+假设!$B$16)/(假设!$B$29-假设!$B$16) -> 8317.8109
A29: 终值现值 | B29: =B28*M19 -> 3735.4022
A30: 企业价值 EV | B30: =B27+B29 -> 5817.2312
A31: 加：净现金 | B31: =假设!$B$31 -> 175.4
A32: 减：少数股东权益 | B32: =-假设!$B$24 -> -200
A33: 股权价值（亿元） | B33: =B30+B31+B32 -> 5792.6312
A34: 每股价值（人民币） | B34: =B33/假设!$B$7 -> 63.536594
A35: 每股价值（港元） | B35: =B34/假设!$B$6 -> 69.820432
A36: 当前 H 股股价（港元） | B36: =假设!$B$5 -> 72.95
A37: 上行/下行空间 | B37: =B35/B36-1 -> -0.042900172
A38: 终值占 EV 比重 | B38: =B29/B30 -> 0.64212716
A39: 隐含 EV / 2027E EBIT | B39: =B30/E8 -> 13.813215

Sheet 敏感性
A1: 每股价值（港元）敏感性：WACC × 永续增长率
A2: 每格独立重算全部 FCFF 折现与终值（使用 DCF 页现金流），非 Excel 数据表
A4: WACC ↓ / g → | B4: 0.015 | C4: 0.02 | D4: 0.025 | E4: 0.03 | F4: 0.035
A5: 0.075 | B5: =(SUMPRODUCT(DCF!$D$16:$M$16,1/(1+$A5)^DCF!$D$18:$M$18)-DCF!$D$16*(1-假设!$B$30)/(1+$A5)^DCF!$D$18+DCF!$M$16*(1+B$4)/($A5-B$4)/(1+$A5)^DCF!$M$18+(假设!$B$31-假设!$B$24))/假设!$B$7/假设!$B$6 -> 82.709647 | C5: =(SUMPRODUCT(DCF!$D$16:$M$16,1/(1+$A5)^DCF!$D$18:$M$18)-DCF!$D$16*(1-假设!$B$30)/(1+$A5)^DCF!$D$18+DCF!$M$16*(1+C$4)/($A5-C$4)/(1+$A5)^DCF!$M$18+(假设!$B$31-假设!$B$24))/假设!$B$7/假设!$B$6 -> 88.077801 | D5: =(SUMPRODUCT(DCF!$D$16:$M$16,1/(1+$A5)^DCF!$D$18:$M$18)-DCF!$D$16*(1-假设!$B$30)/(1+$A5)^DCF!$D$18+DCF!$M$16*(1+D$4)/($A5-D$4)/(1+$A5)^DCF!$M$18+(假设!$B$31-假设!$B$24))/假设!$B$7/假设!$B$6 -> 94.519585 | E5: =(SUMPRODUCT(DCF!$D$16:$M$16,1/(1+$A5)^DCF!$D$18:$M$18)-DCF!$D$16*(1-假设!$B$30)/(1+$A5)^DCF!$D$18+DCF!$M$16*(1+E$4)/($A5-E$4)/(1+$A5)^DCF!$M$18+(假设!$B$31-假设!$B$24))/假设!$B$7/假设!$B$6 -> 102.39288 | F5: =(SUMPRODUCT(DCF!$D$16:$M$16,1/(1+$A5)^DCF!$D$18:$M$18)-DCF!$D$16*(1-假设!$B$30)/(1+$A5)^DCF!$D$18+DCF!$M$16*(1+F$4)/($A5-F$4)/(1+$A5)^DCF!$M$18+(假设!$B$31-假设!$B$24))/假设!$B$7/假设!$B$6 -> 112.23449
A6: 0.08 | B6: =(SUMPRODUCT(DCF!$D$16:$M$16,1/(1+$A6)^DCF!$D$18:$M$18)-DCF!$D$16*(1-假设!$B$30)/(1+$A6)^DCF!$D$18+DCF!$M$16*(1+B$4)/($A6-B$4)/(1+$A6)^DCF!$M$18+(假设!$B$31-假设!$B$24))/假设!$B$7/假设!$B$6 -> 75.548843 | C6: =(SUMPRODUCT(DCF!$D$16:$M$16,1/(1+$A6)^DCF!$D$18:$M$18)-DCF!$D$16*(1-假设!$B$30)/(1+$A6)^DCF!$D$18+DCF!$M$16*(1+C$4)/($A6-C$4)/(1+$A6)^DCF!$M$18+(假设!$B$31-假设!$B$24))/假设!$B$7/假设!$B$6 -> 79.921034 | D6: =(SUMPRODUCT(DCF!$D$16:$M$16,1/(1+$A6)^DCF!$D$18:$M$18)-DCF!$D$16*(1-假设!$B$30)/(1+$A6)^DCF!$D$18+DCF!$M$16*(1+D$4)/($A6-D$4)/(1+$A6)^DCF!$M$18+(假设!$B$31-假设!$B$24))/假设!$B$7/假设!$B$6 -> 85.08817 | E6: =(SUMPRODUCT(DCF!$D$16:$M$16,1/(1+$A6)^DCF!$D$18:$M$18)-DCF!$D$16*(1-假设!$B$30)/(1+$A6)^DCF!$D$18+DCF!$M$16*(1+E$4)/($A6-E$4)/(1+$A6)^DCF!$M$18+(假设!$B$31-假设!$B$24))/假设!$B$7/假设!$B$6 -> 91.288732 | F6: =(SUMPRODUCT(DCF!$D$16:$M$16,1/(1+$A6)^DCF!$D$18:$M$18)-DCF!$D$16*(1-假设!$B$30)/(1+$A6)^DCF!$D$18+DCF!$M$16*(1+F$4)/($A6-F$4)/(1+$A6)^DCF!$M$18+(假设!$B$31-假设!$B$24))/假设!$B$7/假设!$B$6 -> 98.867197
A7: 0.085 | B7: =(SUMPRODUCT(DCF!$D$16:$M$16,1/(1+$A7)^DCF!$D$18:$M$18)-DCF!$D$16*(1-假设!$B$30)/(1+$A7)^DCF!$D$18+DCF!$M$16*(1+B$4)/($A7-B$4)/(1+$A7)^DCF!$M$18+(假设!$B$31-假设!$B$24))/假设!$B$7/假设!$B$6 -> 69.426232 | C7: =(SUMPRODUCT(DCF!$D$16:$M$16,1/(1+$A7)^DCF!$D$18:$M$18)-DCF!$D$16*(1-假设!$B$30)/(1+$A7)^DCF!$D$18+DCF!$M$16*(1+C$4)/($A7-C$4)/(1+$A7)^DCF!$M$18+(假设!$B$31-假设!$B$24))/假设!$B$7/假设!$B$6 -> 73.034126 | D7: =(SUMPRODUCT(DCF!$D$16:$M$16,1/(1+$A7)^DCF!$D$18:$M$18)-DCF!$D$16*(1-假设!$B$30)/(1+$A7)^DCF!$D$18+DCF!$M$16*(1+D$4)/($A7-D$4)/(1+$A7)^DCF!$M$18+(假设!$B$31-假设!$B$24))/假设!$B$7/假设!$B$6 -> 77.243337 | E7: =(SUMPRODUCT(DCF!$D$16:$M$16,1/(1+$A7)^DCF!$D$18:$M$18)-DCF!$D$16*(1-假设!$B$30)/(1+$A7)^DCF!$D$18+DCF!$M$16*(1+E$4)/($A7-E$4)/(1+$A7)^DCF!$M$18+(假设!$B$31-假设!$B$24))/假设!$B$7/假设!$B$6 -> 82.217858 | F7: =(SUMPRODUCT(DCF!$D$16:$M$16,1/(1+$A7)^DCF!$D$18:$M$18)-DCF!$D$16*(1-假设!$B$30)/(1+$A7)^DCF!$D$18+DCF!$M$16*(1+F$4)/($A7-F$4)/(1+$A7)^DCF!$M$18+(假设!$B$31-假设!$B$24))/假设!$B$7/假设!$B$6 -> 88.187284
A8: 0.09 | B8: =(SUMPRODUCT(DCF!$D$16:$M$16,1/(1+$A8)^DCF!$D$18:$M$18)-DCF!$D$16*(1-假设!$B$30)/(1+$A8)^DCF!$D$18+DCF!$M$16*(1+B$4)/($A8-B$4)/(1+$A8)^DCF!$M$18+(假设!$B$31-假设!$B$24))/假设!$B$7/假设!$B$6 -> 64.133747 | C8: =(SUMPRODUCT(DCF!$D$16:$M$16,1/(1+$A8)^DCF!$D$18:$M$18)-DCF!$D$16*(1-假设!$B$30)/(1+$A8)^DCF!$D$18+DCF!$M$16*(1+C$4)/($A8-C$4)/(1+$A8)^DCF!$M$18+(假设!$B$31-假设!$B$24))/假设!$B$7/假设!$B$6 -> 67.144556 | D8: =(SUMPRODUCT(DCF!$D$16:$M$16,1/(1+$A8)^DCF!$D$18:$M$18)-DCF!$D$16*(1-假设!$B$30)/(1+$A8)^DCF!$D$18+DCF!$M$16*(1+D$4)/($A8-D$4)/(1+$A8)^DCF!$M$18+(假设!$B$31-假设!$B$24))/假设!$B$7/假设!$B$6 -> 70.618567 | E8: =(SUMPRODUCT(DCF!$D$16:$M$16,1/(1+$A8)^DCF!$D$18:$M$18)-DCF!$D$16*(1-假设!$B$30)/(1+$A8)^DCF!$D$18+DCF!$M$16*(1+E$4)/($A8-E$4)/(1+$A8)^DCF!$M$18+(假设!$B$31-假设!$B$24))/假设!$B$7/假设!$B$6 -> 74.67158 | F8: =(SUMPRODUCT(DCF!$D$16:$M$16,1/(1+$A8)^DCF!$D$18:$M$18)-DCF!$D$16*(1-假设!$B$30)/(1+$A8)^DCF!$D$18+DCF!$M$16*(1+F$4)/($A8-F$4)/(1+$A8)^DCF!$M$18+(假设!$B$31-假设!$B$24))/假设!$B$7/假设!$B$6 -> 79.461504
A9: 0.095 | B9: =(SUMPRODUCT(DCF!$D$16:$M$16,1/(1+$A9)^DCF!$D$18:$M$18)-DCF!$D$16*(1-假设!$B$30)/(1+$A9)^DCF!$D$18+DCF!$M$16*(1+B$4)/($A9-B$4)/(1+$A9)^DCF!$M$18+(假设!$B$31-假设!$B$24))/假设!$B$7/假设!$B$6 -> 59.515353 | C9: =(SUMPRODUCT(DCF!$D$16:$M$16,1/(1+$A9)^DCF!$D$18:$M$18)-DCF!$D$16*(1-假设!$B$30)/(1+$A9)^DCF!$D$18+DCF!$M$16*(1+C$4)/($A9-C$4)/(1+$A9)^DCF!$M$18+(假设!$B$31-假设!$B$24))/假设!$B$7/假设!$B$6 -> 62.05249 | D9: =(SUMPRODUCT(DCF!$D$16:$M$16,1/(1+$A9)^DCF!$D$18:$M$18)-DCF!$D$16*(1-假设!$B$30)/(1+$A9)^DCF!$D$18+DCF!$M$16*(1+D$4)/($A9-D$4)/(1+$A9)^DCF!$M$18+(假设!$B$31-假设!$B$24))/假设!$B$7/假设!$B$6 -> 64.952075 | E9: =(SUMPRODUCT(DCF!$D$16:$M$16,1/(1+$A9)^DCF!$D$18:$M$18)-DCF!$D$16*(1-假设!$B$30)/(1+$A9)^DCF!$D$18+DCF!$M$16*(1+E$4)/($A9-E$4)/(1+$A9)^DCF!$M$18+(假设!$B$31-假设!$B$24))/假设!$B$7/假设!$B$6 -> 68.297749 | F9: =(SUMPRODUCT(DCF!$D$16:$M$16,1/(1+$A9)^DCF!$D$18:$M$18)-DCF!$D$16*(1-假设!$B$30)/(1+$A9)^DCF!$D$18+DCF!$M$16*(1+F$4)/($A9-F$4)/(1+$A9)^DCF!$M$18+(假设!$B$31-假设!$B$24))/假设!$B$7/假设!$B$6 -> 72.201036
A10: 0.1 | B10: =(SUMPRODUCT(DCF!$D$16:$M$16,1/(1+$A10)^DCF!$D$18:$M$18)-DCF!$D$16*(1-假设!$B$30)/(1+$A10)^DCF!$D$18+DCF!$M$16*(1+B$4)/($A10-B$4)/(1+$A10)^DCF!$M$18+(假设!$B$31-假设!$B$24))/假设!$B$7/假设!$B$6 -> 55.451745 | C10: =(SUMPRODUCT(DCF!$D$16:$M$16,1/(1+$A10)^DCF!$D$18:$M$18)-DCF!$D$16*(1-假设!$B$30)/(1+$A10)^DCF!$D$18+DCF!$M$16*(1+C$4)/($A10-C$4)/(1+$A10)^DCF!$M$18+(假设!$B$31-假设!$B$24))/假设!$B$7/假设!$B$6 -> 57.608064 | D10: =(SUMPRODUCT(DCF!$D$16:$M$16,1/(1+$A10)^DCF!$D$18:$M$18)-DCF!$D$16*(1-假设!$B$30)/(1+$A10)^DCF!$D$18+DCF!$M$16*(1+D$4)/($A10-D$4)/(1+$A10)^DCF!$M$18+(假设!$B$31-假设!$B$24))/假设!$B$7/假设!$B$6 -> 60.051893 | E10: =(SUMPRODUCT(DCF!$D$16:$M$16,1/(1+$A10)^DCF!$D$18:$M$18)-DCF!$D$16*(1-假设!$B$30)/(1+$A10)^DCF!$D$18+DCF!$M$16*(1+E$4)/($A10-E$4)/(1+$A10)^DCF!$M$18+(假设!$B$31-假设!$B$24))/假设!$B$7/假设!$B$6 -> 62.844841 | F10: =(SUMPRODUCT(DCF!$D$16:$M$16,1/(1+$A10)^DCF!$D$18:$M$18)-DCF!$D$16*(1-假设!$B$30)/(1+$A10)^DCF!$D$18+DCF!$M$16*(1+F$4)/($A10-F$4)/(1+$A10)^DCF!$M$18+(假设!$B$31-假设!$B$24))/假设!$B$7/假设!$B$6 -> 66.067472
A11: 0.105 | B11: =(SUMPRODUCT(DCF!$D$16:$M$16,1/(1+$A11)^DCF!$D$18:$M$18)-DCF!$D$16*(1-假设!$B$30)/(1+$A11)^DCF!$D$18+DCF!$M$16*(1+B$4)/($A11-B$4)/(1+$A11)^DCF!$M$18+(假设!$B$31-假设!$B$24))/假设!$B$7/假设!$B$6 -> 51.850139 | C11: =(SUMPRODUCT(DCF!$D$16:$M$16,1/(1+$A11)^DCF!$D$18:$M$18)-DCF!$D$16*(1-假设!$B$30)/(1+$A11)^DCF!$D$18+DCF!$M$16*(1+C$4)/($A11-C$4)/(1+$A11)^DCF!$M$18+(假设!$B$31-假设!$B$24))/假设!$B$7/假设!$B$6 -> 53.69669 | D11: =(SUMPRODUCT(DCF!$D$16:$M$16,1/(1+$A11)^DCF!$D$18:$M$18)-DCF!$D$16*(1-假设!$B$30)/(1+$A11)^DCF!$D$18+DCF!$M$16*(1+D$4)/($A11-D$4)/(1+$A11)^DCF!$M$18+(假设!$B$31-假设!$B$24))/假设!$B$7/假设!$B$6 -> 55.77406 | E11: =(SUMPRODUCT(DCF!$D$16:$M$16,1/(1+$A11)^DCF!$D$18:$M$18)-DCF!$D$16*(1-假设!$B$30)/(1+$A11)^DCF!$D$18+DCF!$M$16*(1+E$4)/($A11-E$4)/(1+$A11)^DCF!$M$18+(假设!$B$31-假设!$B$24))/假设!$B$7/假设!$B$6 -> 58.128413 | F11: =(SUMPRODUCT(DCF!$D$16:$M$16,1/(1+$A11)^DCF!$D$18:$M$18)-DCF!$D$16*(1-假设!$B$30)/(1+$A11)^DCF!$D$18+DCF!$M$16*(1+F$4)/($A11-F$4)/(1+$A11)^DCF!$M$18+(假设!$B$31-假设!$B$24))/假设!$B$7/假设!$B$6 -> 60.819102
A13: 当前 H 股股价 | B13: =假设!$B$5 -> 72.95
A14: 模型 WACC | B14: =假设!$B$29 -> 0.09066

Sheet 来源与说明
A1: 数据来源
A2: 2026 中报：营收 3,448.15 亿（−7.13%），归母净利 123.25 亿（−20.54%），毛利率 18.85%，经营现金流 373.35 亿 — https://stock.10jqka.com.cn/20260829/c679413657.shtml ；https://pdf.dfcfw.com/pdf/H2_AN202608280006758523_1.pdf
A3: 2025 年报：营收 8,039.6 亿，归母净利 326.2 亿，研发 634 亿 — https://www.itiger.com/news/1110052248 ；年报全文 http://notice.10jqka.com.cn/api/pdf/2ecc80f55c9c0abe.pdf
A4: 2025 经营现金流 591.4 亿、资本开支 1,568 亿、折旧估算 — https://caifuhao.eastmoney.com/news/20260414133419735715460 ；https://www.zhihu.com/question/2020984478156239784
A5: 2024 年报：营收 7,771 亿，归母净利 402.54 亿，经营现金流 1,334.53 亿 — https://www.yicai.com/news/102532048.html
A6: 股本 9,117,197,565 股（2025 年 7 月送转后） — https://paper.cnstock.com/html/2026-03/28/content_2193381.htm
A7: H 股股价 72.95 港元（2026-10-08 盘中） — https://gu.qq.com/hk01211/gp/pingji
A9: 主要局限
A10: 1. 资产负债表科目（交易性金融资产、短期借款、少数股东权益）为估算值，请用 2026 中报原文替换 假设 页黄色单元格。
A11: 2. 2025 年 EBIT、折旧为基于净利润和第三方估算推算，非年报直接披露。
A12: 3. 未将大额应付账款/供应链金融视为类债务；若监管压缩账期，营运资本将流出，估值下行。
A13: 4. 使用 A+H 合计股本计算每股价值，隐含假设 A/H 同股同权、无折价。
